Workbook

Sheet CAPA
B1: #VALUE!
B22: Apresentação de Crédito

Sheet RELATÓRIO DE VISITAS
A1: =CAPA!C26 -> 0
A4: RELATÓRIO DE VISITAS

Sheet PROPOSTA
A1: =CAPA!C26 -> 0
A4: Razão Social: | B4: =CAPA!C26 -> 0 | E4: CNPJ:
A6: Relacionamento: | B6: Prospect
A8: Gerente| Plataforma: | B8: Luiz
A10: Analista: | B10: Alyson
A12: PROPOSTA
A13: Modalidade | B13: Limite | C13: Prazo Médio | D13: Tranche | E13: Taxa | F13: Garantia
D14: -
A15: Limite Total | B15: =SUM(B14:B14) -> 0
A17: RATING -
A19: Rating - A - Risco reduzido
A20: Rating - B - Risco médio
A21: Rating - C - Risco elevado
A22: Rating - D - Fora do perfil

Sheet DADOS EMPRESA
A1: =CAPA!C26 -> 0
A4: Data Análise | B4: =TODAY() -> 46036
A5: DADOS GERAIS
A6: Fundação: | C6: =(INT(B4-B6)/365.25) -> 126.0397 | D6: anos
A7: Capital Social:
A8: Unidades | Localização: | B8: Matriz:
A9: Ramo de atividade:
A10: Licenças| Certificações: | B10: Não Informado
A11: Balanço auditado: | B11: Não
A12: Consultoria|Gestão: | B12: Não
A13: Site: | B13: Não possui

Sheet FACHADA
A1: =CAPA!C26 -> 0
A4: FOTO DA EMPRESA (GOOGLE MAPS) FACHADA

Sheet SATELITE
A1: =CAPA!C26 -> 0
A4: FOTO DA EMPRESA (GOOGLE MAPS) FACHADA

Sheet FOTOS
A1: =CAPA!C26 -> 0
A4: FOTOS DA VISITA

Sheet ORGANOGRAMA
A1: =CAPA!C26 -> 0
A4: ORGANOGRAMA

Sheet ESTRUTURA SOCIETÁRIA
A1: =CAPA!C26 -> 0
A4: ESTRUTURA SOCIETÁRIA
A5: Sócios | Diretores | B5: % | C5: Função | Cargo | D5: Figura no Contrato
C6: Sócio | D6: Sim
C7: Sócio | D7: Sim
C8: Sócio | D8: Sim
C9: Sócio | D9: Sim
A10: Assinatura: | B10: ( ) em conjunto | D10: (x) isolada
A11: Aval:
A12: ALTERAÇÕES CONTRATUAIS RELEVANTES
A13: Não

Sheet PATRIMONIO
A1: =CAPA!C26 -> 0
A4: PATRIMONIO DOS SÓCIOS - IRPF 2024/2025
A5: Sócio:
A6: Bens | B6: Valor arrestável R$:
A7: Não possui bens arrestáveis
A8: Total | B8: =SUM(B7:B7) -> 0

Sheet RESTRITIVOS
A1: =CAPA!C26 -> 0
A4: RESTRITIVOS
A5: Empresa/ Sócio | B5: Restritivo | C5: Qntd | D5: Valor | E5: Data | F5: Observação
A6: Nada consta para as empresas e sócios
A7: Totais | C7: =SUM(C6:C6) -> 0 | D7: =SUM(D6:D6) -> 0

Sheet FAT
A1: =CAPA!C26 -> 0
A4: FATURAMENTO CONSOLIDADO
A5: 2025 | C5: ∆ % | D5: 2024 | F5: ∆ % | G5: 2023
A6: 45658 | C6: =B6/E6-1 -> #DIV/0! | D6: 45292 | F6: =E6/H6-1 -> #DIV/0! | G6: 44927
A7: 45689 | C7: =B7/E7-1 -> #DIV/0! | D7: 45323 | F7: =E7/H7-1 -> #DIV/0! | G7: 44958
A8: 45717 | C8: =B8/E8-1 -> #DIV/0! | D8: 45352 | F8: =E8/H8-1 -> #DIV/0! | G8: 44986
A9: 45748 | C9: =B9/E9-1 -> #DIV/0! | D9: 45383 | F9: =E9/H9-1 -> #DIV/0! | G9: 45017
A10: 45778 | C10: =B10/E10-1 -> #DIV/0! | D10: 45413 | F10: =E10/H10-1 -> #DIV/0! | G10: 45047
A11: 45809 | C11: =B11/E11-1 -> #DIV/0! | D11: 45444 | F11: =E11/H11-1 -> #DIV/0! | G11: 45078
A12: 45839 | C12: =B12/E12-1 -> #DIV/0! | D12: 45474 | F12: =E12/H12-1 -> #DIV/0! | G12: 45108
A13: 45870 | C13: =B13/E13-1 -> #DIV/0! | D13: 45505 | F13: =E13/H13-1 -> #DIV/0! | G13: 45139
A14: 45901 | C14: =B14/E14-1 -> #DIV/0! | D14: 45536 | F14: =E14/H14-1 -> #DIV/0! | G14: 45170
A15: 45931 | C15: =B15/E15-1 -> #DIV/0! | D15: 45566 | F15: =E15/H15-1 -> #DIV/0! | G15: 45200
A16: 45962 | C16: =B16/E16-1 -> #DIV/0! | D16: 45597 | F16: =E16/H16-1 -> #DIV/0! | G16: 45231
A17: 45992 | C17: =B17/E17-1 -> #DIV/0! | D17: 45627 | F17: =E17/H17-1 -> #DIV/0! | G17: 45261
A18: TOTAL | B18: =SUM(B6:B17) -> 0 | C18: =C20 -> #DIV/0! | D18: TOTAL | E18: =SUM(E6:E17) -> 0 | F18: =E18/H18-1 -> #DIV/0! | G18: TOTAL | H18: =SUM(H6:H17) -> 0
A19: MÉDIA | B19: =AVERAGE(B6:B16) -> #DIV/0! | C19: 0.01 | D19: MÉDIA | E19: =AVERAGE(E6:E17) -> #DIV/0! | F19: =E19/H19-1 -> #DIV/0! | G19: MÉDIA | H19: =AVERAGE(H6:H17) -> #DIV/0!
A20: MÉDIA ATÉ AGO | B20: =AVERAGE(B6:B13) -> #DIV/0! | C20: =B20/E20-1 -> #DIV/0! | D20: MÉDIA ATÉ AGO | E20: =AVERAGE(E6:E13) -> #DIV/0! | F20: =E20/H20-1 -> #DIV/0! | G20: MÉDIA ATÉ AGO | H20: =AVERAGE(H6:H13) -> #DIV/0!
A21: M. INTERNO: | B21: =B19*C21 -> #DIV/0! | C21: 1 | D21: EXP: | E21: 0 | F21: PAÍSES:

Sheet POTENCIAL
A1: =CAPA!C26 -> 0
A4: POTENCIAL DE NEGÓCIOS
A5: Duplicatas disponíveis para desconto: | B5: =((B9/30)*B15)*B12 -> #DIV/0! | D5: =B5+B6+B7 -> #DIV/0!
A6: Duplicatas disponíveis para comissária: | B6: =((B9/30)*B16)*D12 -> #DIV/0!
A7: Duplicatas disponíveis para Intercompany: | B7: =((B9/30)*B17)*B13 -> #DIV/0!
B8: Potencial real (Vendas a prazo) | D8: =D5*D11 -> #DIV/0!
A9: Faturamento médio M. Interno: | B9: =FAT!B20 -> #DIV/0!
A10: Obs: | B10: Obs: Segundo informações do financeiro em visita na Gávea com Cássio e Fábio: (60% no Atacado e 40% e-commerce). Do atacado 95% paga terceiros. Havan fatura em torno de R$14MM que pode fazer escrow.
A11: Forma do Recebimento: | B11: 0.1 | C11: à vista | D11: 0.9 | E11: a prazo
A12: Composição do Recebimento: | B12: 1 | C12: Duplicatas | D12: 0 | E12: Comissária
C13: Intercompany | E13: Outros
A14: Ticket Médio: | B14: 4000
A15: Prazo Médio de Vendas Dpls: | B15: 75 | C15: dias
A16: Prazo Médio de Vendas Comissária: | B16: 0 | C16: dias
A17: Prazo Médio de Vendas Intercompany: | C17: dias

Sheet ENDIV GERAL
A1: =CAPA!C26 -> 0
A4: ENDIVIDAMENTO BANCOS E FUNDOS
A5: CURTO PRAZO | B5: (%) | C5: LONGO PRAZO | D5: (%) | E5: TOTAL
A6: =B14+B16 -> #REF! | B6: =A6/E6 -> #REF! | C6: =B15 -> 0 | D6: =C6/E6 -> #REF! | E6: =A6+C6 -> #REF!
A7: CURTO PRAZO DPLS | B7: (%) | C7: FUNDOS | D7: (%) | E7: BANCOS | F7: (%)
A8: =B14 -> #REF! | B8: 1 | C8: =B14 -> #REF! | D8: 1 | E8: - | F8: -
C9: RENEGOCIANDO? | E9: () Sim (x) Não
B10: 0 | C10: X Faturamento mês
A11: TOTAL | B11: PELO CEDENTE 01/2025 | C11: POR CONSULTA 01/2025 | D11: LIQ BANCOS E FUNDOS (%) | E11: ∆ %
A12: BANCO E FUNDO | B12: =E6 -> #REF! | E12: -
A14: Desconto fundos | B14: =#REF! -> #REF!
A15: SCR a vencer | B15: 0
B16: 0
A17: TOTAL | B17: =SUM(B14:B16) -> #REF!

Sheet INSTITUIÇÕES
A1: =CAPA!C26 -> 0
A4: ENDIVIDAMENTO COM BANCOS
A5: PELO CEDENTE: | E5: PELO CEDENTE:
A6: INSTITUIÇÃO | B6: MODALIDADE | C6: RISCO | D6: (%) | E6: RISCO | F6: LIQ (%) | G6: VOP
A27: TOTAL | C27: =SUM(C7:C8) -> 0

Sheet REFS FUNDOS (4)
A1: =CAPA!C26 -> 0
A4: INFORMAÇÕES COM FUNDOS | C4: 45979
A5: FUNDO | B5: RW4 | C5: Capitale
A6: Cliente desde:
A7: Última operação:
A8: Limite global:
A9: Risco total:
A10: Risco 1 (R$):
A11: Operação:
A12: Vcto dpls:
A13: Liq até 5 dias:
A14: Liquidez pontual:
A15: Atraso até 5 dias:
A16: Atraso até 15 dias:
A17: Cartório:
... A22: Concentração (%):

Sheet JURIDICO (5)
A1: =CAPA!C26 -> 0
A4: PESQUISAS DE AÇÕES|JURÍDICO DATA: 18/11/2025
A5: Nada consta

Sheet JURIDICO IA
A1: =CAPA!C26 -> 0
A4: PESQUISAS DE AÇÕES|JURÍDICO DATA: 18/11/2025

Sheet NOTICIAS
A1: =CAPA!C26 -> 0
A4: PESQUISAS E NOTÍCIAS DE MÍDIA (EMPRESA|SÓCIOS E COLIGADAS)

Sheet PARECER
A1: =CAPA!C26 -> 0
A4: PARECER DO ANALISTA | B4: DATA: 01/10/2025
A5: ANALISTA | B5: Alyson
A9: Parecer do Diretor Comercial: De acordo com o analista
A11: PROPOSTA
A12: {=PROPOSTA!A14:B14} -> 0 | B12: 0
